{"cf006ece379e7d3d560cac01f2ea7697":{"statistic":{"failed":0,"broken":0,"skipped":1,"passed":0,"unknown":0,"total":1},"items":[{"uid":"d76c529c63cc32a1","reportUrl":"https://nirtal85.github.io/Selenium-Python-Example/464//#testresult/d76c529c63cc32a1","status":"skipped","statusDetails":"Skipped: requires a running VRT server","time":{"start":1731202890319,"stop":1731202890319,"duration":0}}]},"d8696551571014a71a874c85cadaf3fe":{"statistic":{"failed":0,"broken":1,"skipped":0,"passed":0,"unknown":0,"total":1},"items":[{"uid":"a21abf848f5db37f","reportUrl":"https://nirtal85.github.io/Selenium-Python-Example/464//#testresult/a21abf848f5db37f","status":"broken","statusDetails":"selenium.common.exceptions.TimeoutException: Message: \nStacktrace:\n#0 0x56426faac13a <unknown>\n#1 0x56426f5c7460 <unknown>\n#2 0x56426f613f96 <unknown>\n#3 0x56426f614221 <unknown>\n#4 0x56426f6595d4 <unknown>\n#5 0x56426f63803d <unknown>\n#6 0x56426f656af6 <unknown>\n#7 0x56426f637db3 <unknown>\n#8 0x56426f606c10 <unknown>\n#9 0x56426f607bee <unknown>\n#10 0x56426fa783cb <unknown>\n#11 0x56426fa7c368 <unknown>\n#12 0x56426fa65eec <unknown>\n#13 0x56426fa7cee7 <unknown>\n#14 0x56426fa4b13f <unknown>\n#15 0x56426fa9a858 <unknown>\n#16 0x56426fa9aa20 <unknown>\n#17 0x56426faaafb6 <unknown>\n#18 0x7fe2d7694ac3 <unknown>","time":{"start":1731202866648,"stop":1731202876781,"duration":10133}}]},"ed697c69c4643fc2c746342bc96c6608":{"statistic":{"failed":0,"broken":1,"skipped":0,"passed":0,"unknown":0,"total":1},"items":[{"uid":"7bcfb2207cb5d7bf","reportUrl":"https://nirtal85.github.io/Selenium-Python-Example/464//#testresult/7bcfb2207cb5d7bf","status":"broken","statusDetails":"selenium.common.exceptions.TimeoutException: Message: \nStacktrace:\n#0 0x560d2f99f13a <unknown>\n#1 0x560d2f4ba460 <unknown>\n#2 0x560d2f506f96 <unknown>\n#3 0x560d2f507221 <unknown>\n#4 0x560d2f54c5d4 <unknown>\n#5 0x560d2f52b03d <unknown>\n#6 0x560d2f549af6 <unknown>\n#7 0x560d2f52adb3 <unknown>\n#8 0x560d2f4f9c10 <unknown>\n#9 0x560d2f4fabee <unknown>\n#10 0x560d2f96b3cb <unknown>\n#11 0x560d2f96f368 <unknown>\n#12 0x560d2f958eec <unknown>\n#13 0x560d2f96fee7 <unknown>\n#14 0x560d2f93e13f <unknown>\n#15 0x560d2f98d858 <unknown>\n#16 0x560d2f98da20 <unknown>\n#17 0x560d2f99dfb6 <unknown>\n#18 0x7fb5f2c94ac3 <unknown>","time":{"start":1731202956437,"stop":1731202956437,"duration":0}}]},"cd63adf5d11191c5904362b968c9e131":{"statistic":{"failed":0,"broken":1,"skipped":0,"passed":0,"unknown":0,"total":1},"items":[{"uid":"c18dfa35f03ba392","reportUrl":"https://nirtal85.github.io/Selenium-Python-Example/464//#testresult/c18dfa35f03ba392","status":"broken","statusDetails":"selenium.common.exceptions.TimeoutException: Message: \nStacktrace:\n#0 0x56035284e13a <unknown>\n#1 0x560352369460 <unknown>\n#2 0x5603523b5f96 <unknown>\n#3 0x5603523b6221 <unknown>\n#4 0x5603523fb5d4 <unknown>\n#5 0x5603523da03d <unknown>\n#6 0x5603523f8af6 <unknown>\n#7 0x5603523d9db3 <unknown>\n#8 0x5603523a8c10 <unknown>\n#9 0x5603523a9bee <unknown>\n#10 0x56035281a3cb <unknown>\n#11 0x56035281e368 <unknown>\n#12 0x560352807eec <unknown>\n#13 0x56035281eee7 <unknown>\n#14 0x5603527ed13f <unknown>\n#15 0x56035283c858 <unknown>\n#16 0x56035283ca20 <unknown>\n#17 0x56035284cfb6 <unknown>\n#18 0x7fc9d8c94ac3 <unknown>","time":{"start":1731202849531,"stop":1731202849531,"duration":0}}]},"5fb3784879afbb98661f7d2260916ea9":{"statistic":{"failed":0,"broken":0,"skipped":1,"passed":0,"unknown":0,"total":1},"items":[{"uid":"8a5d4422425bd337","reportUrl":"https://nirtal85.github.io/Selenium-Python-Example/464//#testresult/8a5d4422425bd337","status":"skipped","statusDetails":"Skipped: Example only","time":{"start":1731202813369,"stop":1731202813369,"duration":0}}]},"34e866e263d4a1ed453e065aefe8091d":{"statistic":{"failed":0,"broken":1,"skipped":0,"passed":0,"unknown":0,"total":1},"items":[{"uid":"dadbc14631ad2d8b","reportUrl":"https://nirtal85.github.io/Selenium-Python-Example/464//#testresult/dadbc14631ad2d8b","status":"broken","statusDetails":"selenium.common.exceptions.TimeoutException: Message: \nStacktrace:\n#0 0x55d6c9a4613a <unknown>\n#1 0x55d6c9561460 <unknown>\n#2 0x55d6c95adf96 <unknown>\n#3 0x55d6c95ae221 <unknown>\n#4 0x55d6c95f35d4 <unknown>\n#5 0x55d6c95d203d <unknown>\n#6 0x55d6c95f0af6 <unknown>\n#7 0x55d6c95d1db3 <unknown>\n#8 0x55d6c95a0c10 <unknown>\n#9 0x55d6c95a1bee <unknown>\n#10 0x55d6c9a123cb <unknown>\n#11 0x55d6c9a16368 <unknown>\n#12 0x55d6c99ffeec <unknown>\n#13 0x55d6c9a16ee7 <unknown>\n#14 0x55d6c99e513f <unknown>\n#15 0x55d6c9a34858 <unknown>\n#16 0x55d6c9a34a20 <unknown>\n#17 0x55d6c9a44fb6 <unknown>\n#18 0x7f43fe894ac3 <unknown>","time":{"start":1731202910837,"stop":1731202910837,"duration":0}}]},"18657c207d70aa57845e0b7f4751c290":{"statistic":{"failed":0,"broken":1,"skipped":0,"passed":0,"unknown":0,"total":1},"items":[{"uid":"2978afc57c024996","reportUrl":"https://nirtal85.github.io/Selenium-Python-Example/464//#testresult/2978afc57c024996","status":"broken","statusDetails":"selenium.common.exceptions.TimeoutException: Message: \nStacktrace:\n#0 0x5583ce08c13a <unknown>\n#1 0x5583cdba7460 <unknown>\n#2 0x5583cdbf3f96 <unknown>\n#3 0x5583cdbf4221 <unknown>\n#4 0x5583cdc395d4 <unknown>\n#5 0x5583cdc1803d <unknown>\n#6 0x5583cdc36af6 <unknown>\n#7 0x5583cdc17db3 <unknown>\n#8 0x5583cdbe6c10 <unknown>\n#9 0x5583cdbe7bee <unknown>\n#10 0x5583ce0583cb <unknown>\n#11 0x5583ce05c368 <unknown>\n#12 0x5583ce045eec <unknown>\n#13 0x5583ce05cee7 <unknown>\n#14 0x5583ce02b13f <unknown>\n#15 0x5583ce07a858 <unknown>\n#16 0x5583ce07aa20 <unknown>\n#17 0x5583ce08afb6 <unknown>\n#18 0x7f931cc94ac3 <unknown>","time":{"start":1731202861727,"stop":1731202871907,"duration":10180}}]},"01aedc61ee0cb37239b4ba1d780257ea":{"statistic":{"failed":0,"broken":1,"skipped":0,"passed":0,"unknown":0,"total":1},"items":[{"uid":"bb923b5984d13c21","reportUrl":"https://nirtal85.github.io/Selenium-Python-Example/464//#testresult/bb923b5984d13c21","status":"broken","statusDetails":"selenium.common.exceptions.TimeoutException: Message: \nStacktrace:\n#0 0x556c964ce13a <unknown>\n#1 0x556c95fe9460 <unknown>\n#2 0x556c96035f96 <unknown>\n#3 0x556c96036221 <unknown>\n#4 0x556c9607b5d4 <unknown>\n#5 0x556c9605a03d <unknown>\n#6 0x556c96078af6 <unknown>\n#7 0x556c96059db3 <unknown>\n#8 0x556c96028c10 <unknown>\n#9 0x556c96029bee <unknown>\n#10 0x556c9649a3cb <unknown>\n#11 0x556c9649e368 <unknown>\n#12 0x556c96487eec <unknown>\n#13 0x556c9649eee7 <unknown>\n#14 0x556c9646d13f <unknown>\n#15 0x556c964bc858 <unknown>\n#16 0x556c964bca20 <unknown>\n#17 0x556c964ccfb6 <unknown>\n#18 0x7f8b07e94ac3 <unknown>","time":{"start":1731202986925,"stop":1731202986925,"duration":0}}]},"a4f772978b345f2b683ca0dd727dc953":{"statistic":{"failed":0,"broken":0,"skipped":1,"passed":0,"unknown":0,"total":1},"items":[{"uid":"13e7e1ded23c60ec","reportUrl":"https://nirtal85.github.io/Selenium-Python-Example/464//#testresult/13e7e1ded23c60ec","status":"skipped","statusDetails":"Skipped: Example only","time":{"start":1731202813367,"stop":1731202813367,"duration":0}}]},"9dccfec25123dfc886753e91c02a2747":{"statistic":{"failed":0,"broken":0,"skipped":1,"passed":0,"unknown":0,"total":1},"items":[{"uid":"eebebe5bca107e46","reportUrl":"https://nirtal85.github.io/Selenium-Python-Example/464//#testresult/eebebe5bca107e46","status":"skipped","statusDetails":"Skipped: Example only","time":{"start":1731203002341,"stop":1731203002341,"duration":0}}]},"e1f088bc30a040de4100d958931562b3":{"statistic":{"failed":0,"broken":1,"skipped":0,"passed":0,"unknown":0,"total":1},"items":[{"uid":"86ff271b848b29ec","reportUrl":"https://nirtal85.github.io/Selenium-Python-Example/464//#testresult/86ff271b848b29ec","status":"broken","statusDetails":"selenium.common.exceptions.TimeoutException: Message: \nStacktrace:\n#0 0x5641ca82713a <unknown>\n#1 0x5641ca342460 <unknown>\n#2 0x5641ca38ef96 <unknown>\n#3 0x5641ca38f221 <unknown>\n#4 0x5641ca3d45d4 <unknown>\n#5 0x5641ca3b303d <unknown>\n#6 0x5641ca3d1af6 <unknown>\n#7 0x5641ca3b2db3 <unknown>\n#8 0x5641ca381c10 <unknown>\n#9 0x5641ca382bee <unknown>\n#10 0x5641ca7f33cb <unknown>\n#11 0x5641ca7f7368 <unknown>\n#12 0x5641ca7e0eec <unknown>\n#13 0x5641ca7f7ee7 <unknown>\n#14 0x5641ca7c613f <unknown>\n#15 0x5641ca815858 <unknown>\n#16 0x5641ca815a20 <unknown>\n#17 0x5641ca825fb6 <unknown>\n#18 0x7f10e0c94ac3 <unknown>","time":{"start":1731202814680,"stop":1731202814680,"duration":0}}]},"d6dde1715fb973c93e423cd6a34e3dff":{"statistic":{"failed":0,"broken":1,"skipped":0,"passed":0,"unknown":0,"total":1},"items":[{"uid":"be361740089d41c7","reportUrl":"https://nirtal85.github.io/Selenium-Python-Example/464//#testresult/be361740089d41c7","status":"broken","statusDetails":"selenium.common.exceptions.TimeoutException: Message: \nStacktrace:\n#0 0x55a15ab0113a <unknown>\n#1 0x55a15a61c460 <unknown>\n#2 0x55a15a668f96 <unknown>\n#3 0x55a15a669221 <unknown>\n#4 0x55a15a6ae5d4 <unknown>\n#5 0x55a15a68d03d <unknown>\n#6 0x55a15a6abaf6 <unknown>\n#7 0x55a15a68cdb3 <unknown>\n#8 0x55a15a65bc10 <unknown>\n#9 0x55a15a65cbee <unknown>\n#10 0x55a15aacd3cb <unknown>\n#11 0x55a15aad1368 <unknown>\n#12 0x55a15aabaeec <unknown>\n#13 0x55a15aad1ee7 <unknown>\n#14 0x55a15aaa013f <unknown>\n#15 0x55a15aaef858 <unknown>\n#16 0x55a15aaefa20 <unknown>\n#17 0x55a15aafffb6 <unknown>\n#18 0x7fa489494ac3 <unknown>","time":{"start":1731202816088,"stop":1731202826150,"duration":10062}}]},"4e88bda60b0c69cc538a06ace82098c3":{"statistic":{"failed":0,"broken":1,"skipped":0,"passed":0,"unknown":0,"total":1},"items":[{"uid":"ebff0a70ce76b23a","reportUrl":"https://nirtal85.github.io/Selenium-Python-Example/464//#testresult/ebff0a70ce76b23a","status":"broken","statusDetails":"selenium.common.exceptions.TimeoutException: Message: \nStacktrace:\n#0 0x558c31a6c13a <unknown>\n#1 0x558c31587460 <unknown>\n#2 0x558c315d3f96 <unknown>\n#3 0x558c315d4221 <unknown>\n#4 0x558c316195d4 <unknown>\n#5 0x558c315f803d <unknown>\n#6 0x558c31616af6 <unknown>\n#7 0x558c315f7db3 <unknown>\n#8 0x558c315c6c10 <unknown>\n#9 0x558c315c7bee <unknown>\n#10 0x558c31a383cb <unknown>\n#11 0x558c31a3c368 <unknown>\n#12 0x558c31a25eec <unknown>\n#13 0x558c31a3cee7 <unknown>\n#14 0x558c31a0b13f <unknown>\n#15 0x558c31a5a858 <unknown>\n#16 0x558c31a5aa20 <unknown>\n#17 0x558c31a6afb6 <unknown>\n#18 0x7f2c29694ac3 <unknown>","time":{"start":1731202971620,"stop":1731202971620,"duration":0}}]},"ced645a6fd2e72452c1c14188a916149":{"statistic":{"failed":0,"broken":0,"skipped":1,"passed":0,"unknown":0,"total":1},"items":[{"uid":"460e1f0c3a08695a","reportUrl":"https://nirtal85.github.io/Selenium-Python-Example/464//#testresult/460e1f0c3a08695a","status":"skipped","statusDetails":"Skipped: requires database connection","time":{"start":1731203002334,"stop":1731203002334,"duration":0}}]},"288cd0030c92ba34b4ff4b58ed8ec476":{"statistic":{"failed":0,"broken":1,"skipped":0,"passed":0,"unknown":0,"total":1},"items":[{"uid":"798c9e1941c12e81","reportUrl":"https://nirtal85.github.io/Selenium-Python-Example/464//#testresult/798c9e1941c12e81","status":"broken","statusDetails":"selenium.common.exceptions.TimeoutException: Message: \nStacktrace:\n#0 0x5649e510c13a <unknown>\n#1 0x5649e4c27460 <unknown>\n#2 0x5649e4c73f96 <unknown>\n#3 0x5649e4c74221 <unknown>\n#4 0x5649e4cb95d4 <unknown>\n#5 0x5649e4c9803d <unknown>\n#6 0x5649e4cb6af6 <unknown>\n#7 0x5649e4c97db3 <unknown>\n#8 0x5649e4c66c10 <unknown>\n#9 0x5649e4c67bee <unknown>\n#10 0x5649e50d83cb <unknown>\n#11 0x5649e50dc368 <unknown>\n#12 0x5649e50c5eec <unknown>\n#13 0x5649e50dcee7 <unknown>\n#14 0x5649e50ab13f <unknown>\n#15 0x5649e50fa858 <unknown>\n#16 0x5649e50faa20 <unknown>\n#17 0x5649e510afb6 <unknown>\n#18 0x7f58f4a94ac3 <unknown>","time":{"start":1731202831137,"stop":1731202841327,"duration":10190}}]},"0a1c54de755033302b1e39b452f964e0":{"statistic":{"failed":0,"broken":0,"skipped":1,"passed":0,"unknown":0,"total":1},"items":[{"uid":"1a11b858c23e4b64","reportUrl":"https://nirtal85.github.io/Selenium-Python-Example/464//#testresult/1a11b858c23e4b64","status":"skipped","statusDetails":"Skipped: requires a running VRT server","time":{"start":1731202890314,"stop":1731202890314,"duration":0}}]},"7d45847c58512334c984d98e8dbe3df4":{"statistic":{"failed":0,"broken":0,"skipped":1,"passed":0,"unknown":0,"total":1},"items":[{"uid":"9f2f36303232d684","reportUrl":"https://nirtal85.github.io/Selenium-Python-Example/464//#testresult/9f2f36303232d684","status":"skipped","statusDetails":"Skipped: requires mailinator client","time":{"start":1731202813371,"stop":1731202813371,"duration":0}}]},"0e16aaefc41ce304a5aadcc13ecca7ca":{"statistic":{"failed":0,"broken":0,"skipped":1,"passed":0,"unknown":0,"total":1},"items":[{"uid":"dfa52abe47f4b81f","reportUrl":"https://nirtal85.github.io/Selenium-Python-Example/464//#testresult/dfa52abe47f4b81f","status":"skipped","statusDetails":"Skipped: requires a running VRT server","time":{"start":1731202890323,"stop":1731202890323,"duration":0}}]},"8a22eabd564a07b23e060af06cf75254":{"statistic":{"failed":0,"broken":0,"skipped":1,"passed":0,"unknown":0,"total":1},"items":[{"uid":"2c64aa82aa23f0d5","reportUrl":"https://nirtal85.github.io/Selenium-Python-Example/464//#testresult/2c64aa82aa23f0d5","status":"skipped","statusDetails":"Skipped: requires mailinator client","time":{"start":1731202813372,"stop":1731202813372,"duration":0}}]},"d2a250cc6a2f1fc6537c2941dddbd8de":{"statistic":{"failed":0,"broken":0,"skipped":1,"passed":0,"unknown":0,"total":1},"items":[{"uid":"6d5761bec04e7658","reportUrl":"https://nirtal85.github.io/Selenium-Python-Example/464//#testresult/6d5761bec04e7658","status":"skipped","statusDetails":"Skipped: Conditional skip based on base url","time":{"start":1731202829168,"stop":1731202829168,"duration":0}}]},"01ef1df9fb177f8e121dfc0280b56dc3":{"statistic":{"failed":0,"broken":1,"skipped":0,"passed":0,"unknown":0,"total":1},"items":[{"uid":"78d700a9ec4adc","reportUrl":"https://nirtal85.github.io/Selenium-Python-Example/464//#testresult/78d700a9ec4adc","status":"broken","statusDetails":"selenium.common.exceptions.TimeoutException: Message: \nStacktrace:\n#0 0x55b90a2f013a <unknown>\n#1 0x55b909e0b460 <unknown>\n#2 0x55b909e57f96 <unknown>\n#3 0x55b909e58221 <unknown>\n#4 0x55b909e9d5d4 <unknown>\n#5 0x55b909e7c03d <unknown>\n#6 0x55b909e9aaf6 <unknown>\n#7 0x55b909e7bdb3 <unknown>\n#8 0x55b909e4ac10 <unknown>\n#9 0x55b909e4bbee <unknown>\n#10 0x55b90a2bc3cb <unknown>\n#11 0x55b90a2c0368 <unknown>\n#12 0x55b90a2a9eec <unknown>\n#13 0x55b90a2c0ee7 <unknown>\n#14 0x55b90a28f13f <unknown>\n#15 0x55b90a2de858 <unknown>\n#16 0x55b90a2dea20 <unknown>\n#17 0x55b90a2eefb6 <unknown>\n#18 0x7f980c694ac3 <unknown>","time":{"start":1731202877075,"stop":1731202887182,"duration":10107}}]},"16026c2bfd6726335142b41c417320fc":{"statistic":{"failed":0,"broken":0,"skipped":1,"passed":0,"unknown":0,"total":1},"items":[{"uid":"41b1aa36b81dd178","reportUrl":"https://nirtal85.github.io/Selenium-Python-Example/464//#testresult/41b1aa36b81dd178","status":"skipped","statusDetails":"Skipped: skip test example","time":{"start":1731202890310,"stop":1731202890310,"duration":0}}]},"89e36300939846c9ff65d6b54eed8329":{"statistic":{"failed":0,"broken":1,"skipped":0,"passed":0,"unknown":0,"total":1},"items":[{"uid":"a49244222b41d399","reportUrl":"https://nirtal85.github.io/Selenium-Python-Example/464//#testresult/a49244222b41d399","status":"broken","statusDetails":"selenium.common.exceptions.TimeoutException: Message: \nStacktrace:\n#0 0x55c16b87013a <unknown>\n#1 0x55c16b38b460 <unknown>\n#2 0x55c16b3d7f96 <unknown>\n#3 0x55c16b3d8221 <unknown>\n#4 0x55c16b41d5d4 <unknown>\n#5 0x55c16b3fc03d <unknown>\n#6 0x55c16b41aaf6 <unknown>\n#7 0x55c16b3fbdb3 <unknown>\n#8 0x55c16b3cac10 <unknown>\n#9 0x55c16b3cbbee <unknown>\n#10 0x55c16b83c3cb <unknown>\n#11 0x55c16b840368 <unknown>\n#12 0x55c16b829eec <unknown>\n#13 0x55c16b840ee7 <unknown>\n#14 0x55c16b80f13f <unknown>\n#15 0x55c16b85e858 <unknown>\n#16 0x55c16b85ea20 <unknown>\n#17 0x55c16b86efb6 <unknown>\n#18 0x7ff361e94ac3 <unknown>","time":{"start":1731202941280,"stop":1731202941280,"duration":0}}]},"085ae9bea926da8512f07258dfb5df8c":{"statistic":{"failed":0,"broken":1,"skipped":0,"passed":0,"unknown":0,"total":1},"items":[{"uid":"6063c4fc03259835","reportUrl":"https://nirtal85.github.io/Selenium-Python-Example/464//#testresult/6063c4fc03259835","status":"broken","statusDetails":"selenium.common.exceptions.TimeoutException: Message: \nStacktrace:\n#0 0x5631d682613a <unknown>\n#1 0x5631d6341460 <unknown>\n#2 0x5631d638df96 <unknown>\n#3 0x5631d638e221 <unknown>\n#4 0x5631d63d35d4 <unknown>\n#5 0x5631d63b203d <unknown>\n#6 0x5631d63d0af6 <unknown>\n#7 0x5631d63b1db3 <unknown>\n#8 0x5631d6380c10 <unknown>\n#9 0x5631d6381bee <unknown>\n#10 0x5631d67f23cb <unknown>\n#11 0x5631d67f6368 <unknown>\n#12 0x5631d67dfeec <unknown>\n#13 0x5631d67f6ee7 <unknown>\n#14 0x5631d67c513f <unknown>\n#15 0x5631d6814858 <unknown>\n#16 0x5631d6814a20 <unknown>\n#17 0x5631d6824fb6 <unknown>\n#18 0x7f2b62494ac3 <unknown>","time":{"start":1731202895614,"stop":1731202895614,"duration":0}}]},"557b6733f5784cd469824aeac0e8ff06":{"statistic":{"failed":0,"broken":1,"skipped":0,"passed":0,"unknown":0,"total":1},"items":[{"uid":"e8690c1539f79b4e","reportUrl":"https://nirtal85.github.io/Selenium-Python-Example/464//#testresult/e8690c1539f79b4e","status":"broken","statusDetails":"selenium.common.exceptions.TimeoutException: Message: \nStacktrace:\n#0 0x561435f6613a <unknown>\n#1 0x561435a81460 <unknown>\n#2 0x561435acdf96 <unknown>\n#3 0x561435ace221 <unknown>\n#4 0x561435b135d4 <unknown>\n#5 0x561435af203d <unknown>\n#6 0x561435b10af6 <unknown>\n#7 0x561435af1db3 <unknown>\n#8 0x561435ac0c10 <unknown>\n#9 0x561435ac1bee <unknown>\n#10 0x561435f323cb <unknown>\n#11 0x561435f36368 <unknown>\n#12 0x561435f1feec <unknown>\n#13 0x561435f36ee7 <unknown>\n#14 0x561435f0513f <unknown>\n#15 0x561435f54858 <unknown>\n#16 0x561435f54a20 <unknown>\n#17 0x561435f64fb6 <unknown>\n#18 0x7fdd3f694ac3 <unknown>","time":{"start":1731202925923,"stop":1731202925923,"duration":0}}]},"87f81b810de6ee65ae893baebff0ba66":{"statistic":{"failed":0,"broken":0,"skipped":1,"passed":0,"unknown":0,"total":1},"items":[{"uid":"5e6b7e2ace04c635","reportUrl":"https://nirtal85.github.io/Selenium-Python-Example/464//#testresult/5e6b7e2ace04c635","status":"skipped","statusDetails":"Skipped: Example only","time":{"start":1731203002346,"stop":1731203002346,"duration":0}}]},"9bbc2729137fa409b9bc8067987e1d0d":{"statistic":{"failed":0,"broken":1,"skipped":0,"passed":0,"unknown":0,"total":1},"items":[{"uid":"933370a5a4b02800","reportUrl":"https://nirtal85.github.io/Selenium-Python-Example/464//#testresult/933370a5a4b02800","status":"broken","statusDetails":"selenium.common.exceptions.TimeoutException: Message: \nStacktrace:\n#0 0x561bdd4ed13a <unknown>\n#1 0x561bdd008460 <unknown>\n#2 0x561bdd054f96 <unknown>\n#3 0x561bdd055221 <unknown>\n#4 0x561bdd09a5d4 <unknown>\n#5 0x561bdd07903d <unknown>\n#6 0x561bdd097af6 <unknown>\n#7 0x561bdd078db3 <unknown>\n#8 0x561bdd047c10 <unknown>\n#9 0x561bdd048bee <unknown>\n#10 0x561bdd4b93cb <unknown>\n#11 0x561bdd4bd368 <unknown>\n#12 0x561bdd4a6eec <unknown>\n#13 0x561bdd4bdee7 <unknown>\n#14 0x561bdd48c13f <unknown>\n#15 0x561bdd4db858 <unknown>\n#16 0x561bdd4dba20 <unknown>\n#17 0x561bdd4ebfb6 <unknown>\n#18 0x7f1c92294ac3 <unknown>","time":{"start":1731202882354,"stop":1731202892533,"duration":10179}}]},"cb893ca9f67828bed715417c459f87c3":{"statistic":{"failed":0,"broken":0,"skipped":1,"passed":0,"unknown":0,"total":1},"items":[{"uid":"b7a9983a0c765515","reportUrl":"https://nirtal85.github.io/Selenium-Python-Example/464//#testresult/b7a9983a0c765515","status":"skipped","statusDetails":"Skipped: Example only","time":{"start":1731202813370,"stop":1731202813370,"duration":0}}]}}