{"cf006ece379e7d3d560cac01f2ea7697":{"statistic":{"failed":0,"broken":0,"skipped":1,"passed":0,"unknown":0,"total":1},"items":[{"uid":"d4c35acd3cc7a934","reportUrl":"https://nirtal85.github.io/Selenium-Python-Example/467//#testresult/d4c35acd3cc7a934","status":"skipped","statusDetails":"Skipped: requires a running VRT server","time":{"start":1731461901485,"stop":1731461901485,"duration":0}}]},"d8696551571014a71a874c85cadaf3fe":{"statistic":{"failed":0,"broken":1,"skipped":0,"passed":0,"unknown":0,"total":1},"items":[{"uid":"5e63582d8a3b3415","reportUrl":"https://nirtal85.github.io/Selenium-Python-Example/467//#testresult/5e63582d8a3b3415","status":"broken","statusDetails":"selenium.common.exceptions.TimeoutException: Message: \nStacktrace:\n#0 0x55f19e3bd13a <unknown>\n#1 0x55f19ded8460 <unknown>\n#2 0x55f19df24f96 <unknown>\n#3 0x55f19df25221 <unknown>\n#4 0x55f19df6a5d4 <unknown>\n#5 0x55f19df4903d <unknown>\n#6 0x55f19df67af6 <unknown>\n#7 0x55f19df48db3 <unknown>\n#8 0x55f19df17c10 <unknown>\n#9 0x55f19df18bee <unknown>\n#10 0x55f19e3893cb <unknown>\n#11 0x55f19e38d368 <unknown>\n#12 0x55f19e376eec <unknown>\n#13 0x55f19e38dee7 <unknown>\n#14 0x55f19e35c13f <unknown>\n#15 0x55f19e3ab858 <unknown>\n#16 0x55f19e3aba20 <unknown>\n#17 0x55f19e3bbfb6 <unknown>\n#18 0x7f1819094ac3 <unknown>","time":{"start":1731461845070,"stop":1731461855566,"duration":10496}}]},"ed697c69c4643fc2c746342bc96c6608":{"statistic":{"failed":0,"broken":1,"skipped":0,"passed":0,"unknown":0,"total":1},"items":[{"uid":"96d889c572287101","reportUrl":"https://nirtal85.github.io/Selenium-Python-Example/467//#testresult/96d889c572287101","status":"broken","statusDetails":"selenium.common.exceptions.TimeoutException: Message: \nStacktrace:\n#0 0x56272650713a <unknown>\n#1 0x562726022460 <unknown>\n#2 0x56272606ef96 <unknown>\n#3 0x56272606f221 <unknown>\n#4 0x5627260b45d4 <unknown>\n#5 0x56272609303d <unknown>\n#6 0x5627260b1af6 <unknown>\n#7 0x562726092db3 <unknown>\n#8 0x562726061c10 <unknown>\n#9 0x562726062bee <unknown>\n#10 0x5627264d33cb <unknown>\n#11 0x5627264d7368 <unknown>\n#12 0x5627264c0eec <unknown>\n#13 0x5627264d7ee7 <unknown>\n#14 0x5627264a613f <unknown>\n#15 0x5627264f5858 <unknown>\n#16 0x5627264f5a20 <unknown>\n#17 0x562726505fb6 <unknown>\n#18 0x7fc6e9894ac3 <unknown>","time":{"start":1731461934521,"stop":1731461934521,"duration":0}}]},"cd63adf5d11191c5904362b968c9e131":{"statistic":{"failed":0,"broken":1,"skipped":0,"passed":0,"unknown":0,"total":1},"items":[{"uid":"561d6c7af79e36d2","reportUrl":"https://nirtal85.github.io/Selenium-Python-Example/467//#testresult/561d6c7af79e36d2","status":"broken","statusDetails":"selenium.common.exceptions.TimeoutException: Message: \nStacktrace:\n#0 0x5593c8ece13a <unknown>\n#1 0x5593c89e9460 <unknown>\n#2 0x5593c8a35f96 <unknown>\n#3 0x5593c8a36221 <unknown>\n#4 0x5593c8a7b5d4 <unknown>\n#5 0x5593c8a5a03d <unknown>\n#6 0x5593c8a78af6 <unknown>\n#7 0x5593c8a59db3 <unknown>\n#8 0x5593c8a28c10 <unknown>\n#9 0x5593c8a29bee <unknown>\n#10 0x5593c8e9a3cb <unknown>\n#11 0x5593c8e9e368 <unknown>\n#12 0x5593c8e87eec <unknown>\n#13 0x5593c8e9eee7 <unknown>\n#14 0x5593c8e6d13f <unknown>\n#15 0x5593c8ebc858 <unknown>\n#16 0x5593c8ebca20 <unknown>\n#17 0x5593c8eccfb6 <unknown>\n#18 0x7f11e7094ac3 <unknown>","time":{"start":1731461827900,"stop":1731461827900,"duration":0}}]},"510a2d02f67c06d8e402b94edfe2d7d9":{"statistic":{"failed":0,"broken":1,"skipped":0,"passed":0,"unknown":0,"total":1},"items":[{"uid":"92a94c086fde76a7","reportUrl":"https://nirtal85.github.io/Selenium-Python-Example/467//#testresult/92a94c086fde76a7","status":"broken","statusDetails":"selenium.common.exceptions.TimeoutException: Message: \nStacktrace:\n#0 0x5609b817d13a <unknown>\n#1 0x5609b7c98460 <unknown>\n#2 0x5609b7ce4f96 <unknown>\n#3 0x5609b7ce5221 <unknown>\n#4 0x5609b7d2a5d4 <unknown>\n#5 0x5609b7d0903d <unknown>\n#6 0x5609b7d27af6 <unknown>\n#7 0x5609b7d08db3 <unknown>\n#8 0x5609b7cd7c10 <unknown>\n#9 0x5609b7cd8bee <unknown>\n#10 0x5609b81493cb <unknown>\n#11 0x5609b814d368 <unknown>\n#12 0x5609b8136eec <unknown>\n#13 0x5609b814dee7 <unknown>\n#14 0x5609b811c13f <unknown>\n#15 0x5609b816b858 <unknown>\n#16 0x5609b816ba20 <unknown>\n#17 0x5609b817bfb6 <unknown>\n#18 0x7fc283494ac3 <unknown>","time":{"start":1731461887865,"stop":1731461898019,"duration":10154}}]},"5fb3784879afbb98661f7d2260916ea9":{"statistic":{"failed":0,"broken":0,"skipped":1,"passed":0,"unknown":0,"total":1},"items":[{"uid":"9baf4f5963e3ceb2","reportUrl":"https://nirtal85.github.io/Selenium-Python-Example/467//#testresult/9baf4f5963e3ceb2","status":"skipped","statusDetails":"Skipped: Example only","time":{"start":1731461807551,"stop":1731461807551,"duration":0}}]},"34e866e263d4a1ed453e065aefe8091d":{"statistic":{"failed":0,"broken":1,"skipped":0,"passed":0,"unknown":0,"total":1},"items":[{"uid":"f6d42a7e7fb5bdad","reportUrl":"https://nirtal85.github.io/Selenium-Python-Example/467//#testresult/f6d42a7e7fb5bdad","status":"broken","statusDetails":"selenium.common.exceptions.TimeoutException: Message: \nStacktrace:\n#0 0x5654fbdd813a <unknown>\n#1 0x5654fb8f3460 <unknown>\n#2 0x5654fb93ff96 <unknown>\n#3 0x5654fb940221 <unknown>\n#4 0x5654fb9855d4 <unknown>\n#5 0x5654fb96403d <unknown>\n#6 0x5654fb982af6 <unknown>\n#7 0x5654fb963db3 <unknown>\n#8 0x5654fb932c10 <unknown>\n#9 0x5654fb933bee <unknown>\n#10 0x5654fbda43cb <unknown>\n#11 0x5654fbda8368 <unknown>\n#12 0x5654fbd91eec <unknown>\n#13 0x5654fbda8ee7 <unknown>\n#14 0x5654fbd7713f <unknown>\n#15 0x5654fbdc6858 <unknown>\n#16 0x5654fbdc6a20 <unknown>\n#17 0x5654fbdd6fb6 <unknown>\n#18 0x7fba51494ac3 <unknown>","time":{"start":1731461888406,"stop":1731461888406,"duration":0}}]},"18657c207d70aa57845e0b7f4751c290":{"statistic":{"failed":0,"broken":1,"skipped":0,"passed":0,"unknown":0,"total":1},"items":[{"uid":"e1bfe90674435363","reportUrl":"https://nirtal85.github.io/Selenium-Python-Example/467//#testresult/e1bfe90674435363","status":"broken","statusDetails":"selenium.common.exceptions.TimeoutException: Message: \nStacktrace:\n#0 0x55869762613a <unknown>\n#1 0x558697141460 <unknown>\n#2 0x55869718df96 <unknown>\n#3 0x55869718e221 <unknown>\n#4 0x5586971d35d4 <unknown>\n#5 0x5586971b203d <unknown>\n#6 0x5586971d0af6 <unknown>\n#7 0x5586971b1db3 <unknown>\n#8 0x558697180c10 <unknown>\n#9 0x558697181bee <unknown>\n#10 0x5586975f23cb <unknown>\n#11 0x5586975f6368 <unknown>\n#12 0x5586975dfeec <unknown>\n#13 0x5586975f6ee7 <unknown>\n#14 0x5586975c513f <unknown>\n#15 0x558697614858 <unknown>\n#16 0x558697614a20 <unknown>\n#17 0x558697624fb6 <unknown>\n#18 0x7f8763294ac3 <unknown>","time":{"start":1731461871993,"stop":1731461882218,"duration":10225}}]},"01aedc61ee0cb37239b4ba1d780257ea":{"statistic":{"failed":0,"broken":1,"skipped":0,"passed":0,"unknown":0,"total":1},"items":[{"uid":"744d6c51838d920e","reportUrl":"https://nirtal85.github.io/Selenium-Python-Example/467//#testresult/744d6c51838d920e","status":"broken","statusDetails":"selenium.common.exceptions.TimeoutException: Message: \nStacktrace:\n#0 0x561d2979713a <unknown>\n#1 0x561d292b2460 <unknown>\n#2 0x561d292fef96 <unknown>\n#3 0x561d292ff221 <unknown>\n#4 0x561d293445d4 <unknown>\n#5 0x561d2932303d <unknown>\n#6 0x561d29341af6 <unknown>\n#7 0x561d29322db3 <unknown>\n#8 0x561d292f1c10 <unknown>\n#9 0x561d292f2bee <unknown>\n#10 0x561d297633cb <unknown>\n#11 0x561d29767368 <unknown>\n#12 0x561d29750eec <unknown>\n#13 0x561d29767ee7 <unknown>\n#14 0x561d2973613f <unknown>\n#15 0x561d29785858 <unknown>\n#16 0x561d29785a20 <unknown>\n#17 0x561d29795fb6 <unknown>\n#18 0x7f0795894ac3 <unknown>","time":{"start":1731461966519,"stop":1731461966519,"duration":0}}]},"a4f772978b345f2b683ca0dd727dc953":{"statistic":{"failed":0,"broken":0,"skipped":1,"passed":0,"unknown":0,"total":1},"items":[{"uid":"524c034e3f7edb63","reportUrl":"https://nirtal85.github.io/Selenium-Python-Example/467//#testresult/524c034e3f7edb63","status":"skipped","statusDetails":"Skipped: Example only","time":{"start":1731461807549,"stop":1731461807549,"duration":0}}]},"9dccfec25123dfc886753e91c02a2747":{"statistic":{"failed":0,"broken":0,"skipped":1,"passed":0,"unknown":0,"total":1},"items":[{"uid":"bd9fed172dcc522b","reportUrl":"https://nirtal85.github.io/Selenium-Python-Example/467//#testresult/bd9fed172dcc522b","status":"skipped","statusDetails":"Skipped: Example only","time":{"start":1731461983351,"stop":1731461983351,"duration":0}}]},"e1f088bc30a040de4100d958931562b3":{"statistic":{"failed":0,"broken":1,"skipped":0,"passed":0,"unknown":0,"total":1},"items":[{"uid":"9c61ead28d76d9c","reportUrl":"https://nirtal85.github.io/Selenium-Python-Example/467//#testresult/9c61ead28d76d9c","status":"broken","statusDetails":"selenium.common.exceptions.TimeoutException: Message: \nStacktrace:\n#0 0x561a0e31613a <unknown>\n#1 0x561a0de31460 <unknown>\n#2 0x561a0de7df96 <unknown>\n#3 0x561a0de7e221 <unknown>\n#4 0x561a0dec35d4 <unknown>\n#5 0x561a0dea203d <unknown>\n#6 0x561a0dec0af6 <unknown>\n#7 0x561a0dea1db3 <unknown>\n#8 0x561a0de70c10 <unknown>\n#9 0x561a0de71bee <unknown>\n#10 0x561a0e2e23cb <unknown>\n#11 0x561a0e2e6368 <unknown>\n#12 0x561a0e2cfeec <unknown>\n#13 0x561a0e2e6ee7 <unknown>\n#14 0x561a0e2b513f <unknown>\n#15 0x561a0e304858 <unknown>\n#16 0x561a0e304a20 <unknown>\n#17 0x561a0e314fb6 <unknown>\n#18 0x7f30d4c94ac3 <unknown>","time":{"start":1731461805818,"stop":1731461805818,"duration":0}}]},"4e88bda60b0c69cc538a06ace82098c3":{"statistic":{"failed":0,"broken":1,"skipped":0,"passed":0,"unknown":0,"total":1},"items":[{"uid":"b7fdf64d42b1dd3","reportUrl":"https://nirtal85.github.io/Selenium-Python-Example/467//#testresult/b7fdf64d42b1dd3","status":"broken","statusDetails":"selenium.common.exceptions.TimeoutException: Message: \nStacktrace:\n#0 0x55dc6af1a13a <unknown>\n#1 0x55dc6aa35460 <unknown>\n#2 0x55dc6aa81f96 <unknown>\n#3 0x55dc6aa82221 <unknown>\n#4 0x55dc6aac75d4 <unknown>\n#5 0x55dc6aaa603d <unknown>\n#6 0x55dc6aac4af6 <unknown>\n#7 0x55dc6aaa5db3 <unknown>\n#8 0x55dc6aa74c10 <unknown>\n#9 0x55dc6aa75bee <unknown>\n#10 0x55dc6aee63cb <unknown>\n#11 0x55dc6aeea368 <unknown>\n#12 0x55dc6aed3eec <unknown>\n#13 0x55dc6aeeaee7 <unknown>\n#14 0x55dc6aeb913f <unknown>\n#15 0x55dc6af08858 <unknown>\n#16 0x55dc6af08a20 <unknown>\n#17 0x55dc6af18fb6 <unknown>\n#18 0x7fc801894ac3 <unknown>","time":{"start":1731461949894,"stop":1731461949894,"duration":0}}]},"d6dde1715fb973c93e423cd6a34e3dff":{"statistic":{"failed":0,"broken":1,"skipped":0,"passed":0,"unknown":0,"total":1},"items":[{"uid":"54cfc8312a5f274a","reportUrl":"https://nirtal85.github.io/Selenium-Python-Example/467//#testresult/54cfc8312a5f274a","status":"broken","statusDetails":"selenium.common.exceptions.TimeoutException: Message: \nStacktrace:\n#0 0x560749f1613a <unknown>\n#1 0x560749a31460 <unknown>\n#2 0x560749a7df96 <unknown>\n#3 0x560749a7e221 <unknown>\n#4 0x560749ac35d4 <unknown>\n#5 0x560749aa203d <unknown>\n#6 0x560749ac0af6 <unknown>\n#7 0x560749aa1db3 <unknown>\n#8 0x560749a70c10 <unknown>\n#9 0x560749a71bee <unknown>\n#10 0x560749ee23cb <unknown>\n#11 0x560749ee6368 <unknown>\n#12 0x560749ecfeec <unknown>\n#13 0x560749ee6ee7 <unknown>\n#14 0x560749eb513f <unknown>\n#15 0x560749f04858 <unknown>\n#16 0x560749f04a20 <unknown>\n#17 0x560749f14fb6 <unknown>\n#18 0x7fdbddc94ac3 <unknown>","time":{"start":1731461823551,"stop":1731461833568,"duration":10017}}]},"ced645a6fd2e72452c1c14188a916149":{"statistic":{"failed":0,"broken":0,"skipped":1,"passed":0,"unknown":0,"total":1},"items":[{"uid":"589877f220c9317a","reportUrl":"https://nirtal85.github.io/Selenium-Python-Example/467//#testresult/589877f220c9317a","status":"skipped","statusDetails":"Skipped: requires database connection","time":{"start":1731461983347,"stop":1731461983347,"duration":0}}]},"288cd0030c92ba34b4ff4b58ed8ec476":{"statistic":{"failed":0,"broken":1,"skipped":0,"passed":0,"unknown":0,"total":1},"items":[{"uid":"f23cf30d97b3b2be","reportUrl":"https://nirtal85.github.io/Selenium-Python-Example/467//#testresult/f23cf30d97b3b2be","status":"broken","statusDetails":"selenium.common.exceptions.TimeoutException: Message: \nStacktrace:\n#0 0x55aec3e2013a <unknown>\n#1 0x55aec393b460 <unknown>\n#2 0x55aec3987f96 <unknown>\n#3 0x55aec3988221 <unknown>\n#4 0x55aec39cd5d4 <unknown>\n#5 0x55aec39ac03d <unknown>\n#6 0x55aec39caaf6 <unknown>\n#7 0x55aec39abdb3 <unknown>\n#8 0x55aec397ac10 <unknown>\n#9 0x55aec397bbee <unknown>\n#10 0x55aec3dec3cb <unknown>\n#11 0x55aec3df0368 <unknown>\n#12 0x55aec3dd9eec <unknown>\n#13 0x55aec3df0ee7 <unknown>\n#14 0x55aec3dbf13f <unknown>\n#15 0x55aec3e0e858 <unknown>\n#16 0x55aec3e0ea20 <unknown>\n#17 0x55aec3e1efb6 <unknown>\n#18 0x7fb9df294ac3 <unknown>","time":{"start":1731461839164,"stop":1731461849235,"duration":10071}}]},"0a1c54de755033302b1e39b452f964e0":{"statistic":{"failed":0,"broken":0,"skipped":1,"passed":0,"unknown":0,"total":1},"items":[{"uid":"cbbde07a0963442c","reportUrl":"https://nirtal85.github.io/Selenium-Python-Example/467//#testresult/cbbde07a0963442c","status":"skipped","statusDetails":"Skipped: requires a running VRT server","time":{"start":1731461901480,"stop":1731461901480,"duration":0}}]},"0e16aaefc41ce304a5aadcc13ecca7ca":{"statistic":{"failed":0,"broken":0,"skipped":1,"passed":0,"unknown":0,"total":1},"items":[{"uid":"226ef5b28c51953e","reportUrl":"https://nirtal85.github.io/Selenium-Python-Example/467//#testresult/226ef5b28c51953e","status":"skipped","statusDetails":"Skipped: requires a running VRT server","time":{"start":1731461901490,"stop":1731461901490,"duration":0}}]},"7d45847c58512334c984d98e8dbe3df4":{"statistic":{"failed":0,"broken":0,"skipped":1,"passed":0,"unknown":0,"total":1},"items":[{"uid":"64bfc9c72d5facce","reportUrl":"https://nirtal85.github.io/Selenium-Python-Example/467//#testresult/64bfc9c72d5facce","status":"skipped","statusDetails":"Skipped: requires mailinator client","time":{"start":1731461807553,"stop":1731461807553,"duration":0}}]},"8a22eabd564a07b23e060af06cf75254":{"statistic":{"failed":0,"broken":0,"skipped":1,"passed":0,"unknown":0,"total":1},"items":[{"uid":"52881e3fbb279e8d","reportUrl":"https://nirtal85.github.io/Selenium-Python-Example/467//#testresult/52881e3fbb279e8d","status":"skipped","statusDetails":"Skipped: requires mailinator client","time":{"start":1731461807554,"stop":1731461807554,"duration":0}}]},"d2a250cc6a2f1fc6537c2941dddbd8de":{"statistic":{"failed":0,"broken":0,"skipped":1,"passed":0,"unknown":0,"total":1},"items":[{"uid":"d50fbcd79199c57b","reportUrl":"https://nirtal85.github.io/Selenium-Python-Example/467//#testresult/d50fbcd79199c57b","status":"skipped","statusDetails":"Skipped: Conditional skip based on base url","time":{"start":1731461836890,"stop":1731461836890,"duration":0}}]},"16026c2bfd6726335142b41c417320fc":{"statistic":{"failed":0,"broken":0,"skipped":1,"passed":0,"unknown":0,"total":1},"items":[{"uid":"2bf42719e3b51397","reportUrl":"https://nirtal85.github.io/Selenium-Python-Example/467//#testresult/2bf42719e3b51397","status":"skipped","statusDetails":"Skipped: skip test example","time":{"start":1731461901475,"stop":1731461901475,"duration":0}}]},"89e36300939846c9ff65d6b54eed8329":{"statistic":{"failed":0,"broken":1,"skipped":0,"passed":0,"unknown":0,"total":1},"items":[{"uid":"c7ff78e5d24ea6f9","reportUrl":"https://nirtal85.github.io/Selenium-Python-Example/467//#testresult/c7ff78e5d24ea6f9","status":"broken","statusDetails":"selenium.common.exceptions.TimeoutException: Message: \nStacktrace:\n#0 0x55c8cb99c13a <unknown>\n#1 0x55c8cb4b7460 <unknown>\n#2 0x55c8cb503f96 <unknown>\n#3 0x55c8cb504221 <unknown>\n#4 0x55c8cb5495d4 <unknown>\n#5 0x55c8cb52803d <unknown>\n#6 0x55c8cb546af6 <unknown>\n#7 0x55c8cb527db3 <unknown>\n#8 0x55c8cb4f6c10 <unknown>\n#9 0x55c8cb4f7bee <unknown>\n#10 0x55c8cb9683cb <unknown>\n#11 0x55c8cb96c368 <unknown>\n#12 0x55c8cb955eec <unknown>\n#13 0x55c8cb96cee7 <unknown>\n#14 0x55c8cb93b13f <unknown>\n#15 0x55c8cb98a858 <unknown>\n#16 0x55c8cb98aa20 <unknown>\n#17 0x55c8cb99afb6 <unknown>\n#18 0x7f306cc94ac3 <unknown>","time":{"start":1731461919107,"stop":1731461919107,"duration":0}}]},"085ae9bea926da8512f07258dfb5df8c":{"statistic":{"failed":0,"broken":1,"skipped":0,"passed":0,"unknown":0,"total":1},"items":[{"uid":"a26ae2c6dd4b40bc","reportUrl":"https://nirtal85.github.io/Selenium-Python-Example/467//#testresult/a26ae2c6dd4b40bc","status":"broken","statusDetails":"selenium.common.exceptions.TimeoutException: Message: \nStacktrace:\n#0 0x55b828c9f13a <unknown>\n#1 0x55b8287ba460 <unknown>\n#2 0x55b828806f96 <unknown>\n#3 0x55b828807221 <unknown>\n#4 0x55b82884c5d4 <unknown>\n#5 0x55b82882b03d <unknown>\n#6 0x55b828849af6 <unknown>\n#7 0x55b82882adb3 <unknown>\n#8 0x55b8287f9c10 <unknown>\n#9 0x55b8287fabee <unknown>\n#10 0x55b828c6b3cb <unknown>\n#11 0x55b828c6f368 <unknown>\n#12 0x55b828c58eec <unknown>\n#13 0x55b828c6fee7 <unknown>\n#14 0x55b828c3e13f <unknown>\n#15 0x55b828c8d858 <unknown>\n#16 0x55b828c8da20 <unknown>\n#17 0x55b828c9dfb6 <unknown>\n#18 0x7f8ae6694ac3 <unknown>","time":{"start":1731461873393,"stop":1731461873393,"duration":0}}]},"557b6733f5784cd469824aeac0e8ff06":{"statistic":{"failed":0,"broken":1,"skipped":0,"passed":0,"unknown":0,"total":1},"items":[{"uid":"79ef05ec33cc7237","reportUrl":"https://nirtal85.github.io/Selenium-Python-Example/467//#testresult/79ef05ec33cc7237","status":"broken","statusDetails":"selenium.common.exceptions.TimeoutException: Message: \nStacktrace:\n#0 0x558a4659413a <unknown>\n#1 0x558a460af460 <unknown>\n#2 0x558a460fbf96 <unknown>\n#3 0x558a460fc221 <unknown>\n#4 0x558a461415d4 <unknown>\n#5 0x558a4612003d <unknown>\n#6 0x558a4613eaf6 <unknown>\n#7 0x558a4611fdb3 <unknown>\n#8 0x558a460eec10 <unknown>\n#9 0x558a460efbee <unknown>\n#10 0x558a465603cb <unknown>\n#11 0x558a46564368 <unknown>\n#12 0x558a4654deec <unknown>\n#13 0x558a46564ee7 <unknown>\n#14 0x558a4653313f <unknown>\n#15 0x558a46582858 <unknown>\n#16 0x558a46582a20 <unknown>\n#17 0x558a46592fb6 <unknown>\n#18 0x7fc021094ac3 <unknown>","time":{"start":1731461903651,"stop":1731461903651,"duration":0}}]},"87f81b810de6ee65ae893baebff0ba66":{"statistic":{"failed":0,"broken":0,"skipped":1,"passed":0,"unknown":0,"total":1},"items":[{"uid":"ce688669911e17b8","reportUrl":"https://nirtal85.github.io/Selenium-Python-Example/467//#testresult/ce688669911e17b8","status":"skipped","statusDetails":"Skipped: Example only","time":{"start":1731461983355,"stop":1731461983355,"duration":0}}]},"9bbc2729137fa409b9bc8067987e1d0d":{"statistic":{"failed":0,"broken":1,"skipped":0,"passed":0,"unknown":0,"total":1},"items":[{"uid":"d63f1c26f5525a79","reportUrl":"https://nirtal85.github.io/Selenium-Python-Example/467//#testresult/d63f1c26f5525a79","status":"broken","statusDetails":"selenium.common.exceptions.TimeoutException: Message: \nStacktrace:\n#0 0x56446874313a <unknown>\n#1 0x56446825e460 <unknown>\n#2 0x5644682aaf96 <unknown>\n#3 0x5644682ab221 <unknown>\n#4 0x5644682f05d4 <unknown>\n#5 0x5644682cf03d <unknown>\n#6 0x5644682edaf6 <unknown>\n#7 0x5644682cedb3 <unknown>\n#8 0x56446829dc10 <unknown>\n#9 0x56446829ebee <unknown>\n#10 0x56446870f3cb <unknown>\n#11 0x564468713368 <unknown>\n#12 0x5644686fceec <unknown>\n#13 0x564468713ee7 <unknown>\n#14 0x5644686e213f <unknown>\n#15 0x564468731858 <unknown>\n#16 0x564468731a20 <unknown>\n#17 0x564468741fb6 <unknown>\n#18 0x7f3401094ac3 <unknown>","time":{"start":1731461860279,"stop":1731461870712,"duration":10433}}]},"cb893ca9f67828bed715417c459f87c3":{"statistic":{"failed":0,"broken":0,"skipped":1,"passed":0,"unknown":0,"total":1},"items":[{"uid":"e884bf677ac91c73","reportUrl":"https://nirtal85.github.io/Selenium-Python-Example/467//#testresult/e884bf677ac91c73","status":"skipped","statusDetails":"Skipped: Example only","time":{"start":1731461807552,"stop":1731461807552,"duration":0}}]}}